[

  {
    "name": "Димасик Бобылев",
    "email": "prostreet1212@gmail.com"
  },
  {
    "name": "Димасик Бобылев",
    "email": "prostreet1212@gmail.com"
  },
  {
    "name": "Димасик Бобылев",
    "email": "prostreet1212@gmail.com"
  },
  {
    "name": "Димасик Бобылев",
    "email": "prostreet1212@gmail.com"
  },
  {
    "name": "Димасик Бобылев",
    "email": "prostreet1212@gmail.com"
  },
  {
    "name": "Димасик Бобылев",
    "email": "prostreet1212@gmail.com"
  },
  {
    "name": "Димасик Бобылев",
    "email": "prostreet1212@gmail.com"
  },
  {
    "name": "Димасик Бобылев",
    "email": "prostreet1212@gmail.com"
  },
  {
    "name": "Димасик Бобылев",
    "email": "prostreet1212@gmail.com"
  },
  {
    "name": "Димасик Бобылев",
    "email": "prostreet1212@gmail.com"
  }
]
